npc/futurecore/sim/logs/annotated/FutureCore.sv
//      // verilator_coverage annotation
        // Generated by CIRCT firtool-1.62.0
        // Standard header to adapt well known macros for register randomization.
        `ifndef RANDOMIZE
          `ifdef RANDOMIZE_REG_INIT
            `define RANDOMIZE
          `endif // RANDOMIZE_REG_INIT
        `endif // not def RANDOMIZE
        
        // RANDOM may be set to an expression that produces a 32-bit random unsigned value.
        `ifndef RANDOM
          `define RANDOM $random
        `endif // not def RANDOM
        
        // Users can define INIT_RANDOM as general code that gets injected into the
        // initializer block for modules with registers.
        `ifndef INIT_RANDOM
          `define INIT_RANDOM
        `endif // not def INIT_RANDOM
        
        // If using random initialization, you can also define RANDOMIZE_DELAY to
        // customize the delay used, otherwise 0.002 is used.
        `ifndef RANDOMIZE_DELAY
          `define RANDOMIZE_DELAY 0.002
        `endif // not def RANDOMIZE_DELAY
        
        // Define INIT_RANDOM_PROLOG_ for use in our modules below.
        `ifndef INIT_RANDOM_PROLOG_
          `ifdef RANDOMIZE
            `ifdef VERILATOR
              `define INIT_RANDOM_PROLOG_ `INIT_RANDOM
            `else  // VERILATOR
              `define INIT_RANDOM_PROLOG_ `INIT_RANDOM #`RANDOMIZE_DELAY begin end
            `endif // VERILATOR
          `else  // RANDOMIZE
            `define INIT_RANDOM_PROLOG_
          `endif // RANDOMIZE
        `endif // not def INIT_RANDOM_PROLOG_
        
        // Include register initializers in init blocks unless synthesis is set
        `ifndef SYNTHESIS
          `ifndef ENABLE_INITIAL_REG_
            `define ENABLE_INITIAL_REG_
          `endif // not def ENABLE_INITIAL_REG_
        `endif // not def SYNTHESIS
        
        // Include rmemory initializers in init blocks unless synthesis is set
        `ifndef SYNTHESIS
          `ifndef ENABLE_INITIAL_MEM_
            `define ENABLE_INITIAL_MEM_
          `endif // not def ENABLE_INITIAL_MEM_
        `endif // not def SYNTHESIS
        
        module ProgramCounter(	// futurecore/src/main/scala/frontend/ProgramCounter.scala:9:7
 000100   input         clock,	// <stdin>:15:11
%000002                 reset,	// <stdin>:16:11
%000000   output [31:0] io_instAddr	// futurecore/src/main/scala/frontend/ProgramCounter.scala:10:21
        );
        
%000000   reg [31:0] pc;	// futurecore/src/main/scala/frontend/ProgramCounter.scala:13:26
 000049   always @(posedge clock) begin	// <stdin>:15:11
%000004     if (reset)	// <stdin>:15:11
%000004       pc <= 32'h0;	// futurecore/src/main/scala/frontend/ProgramCounter.scala:13:26
            else	// <stdin>:15:11
 000045       pc <= pc + 32'h4;	// futurecore/src/main/scala/frontend/ProgramCounter.scala:13:26, :14:12
          end // always @(posedge)
          `ifdef ENABLE_INITIAL_REG_	// futurecore/src/main/scala/frontend/ProgramCounter.scala:9:7
            `ifdef FIRRTL_BEFORE_INITIAL	// futurecore/src/main/scala/frontend/ProgramCounter.scala:9:7
              `FIRRTL_BEFORE_INITIAL	// futurecore/src/main/scala/frontend/ProgramCounter.scala:9:7
            `endif // FIRRTL_BEFORE_INITIAL
%000001     initial begin	// futurecore/src/main/scala/frontend/ProgramCounter.scala:9:7
              automatic logic [31:0] _RANDOM[0:0];	// futurecore/src/main/scala/frontend/ProgramCounter.scala:9:7
              `ifdef INIT_RANDOM_PROLOG_	// futurecore/src/main/scala/frontend/ProgramCounter.scala:9:7
                `INIT_RANDOM_PROLOG_	// futurecore/src/main/scala/frontend/ProgramCounter.scala:9:7
              `endif // INIT_RANDOM_PROLOG_
              `ifdef RANDOMIZE_REG_INIT	// futurecore/src/main/scala/frontend/ProgramCounter.scala:9:7
                _RANDOM[/*Zero width*/ 1'b0] = `RANDOM;	// futurecore/src/main/scala/frontend/ProgramCounter.scala:9:7
                pc = _RANDOM[/*Zero width*/ 1'b0];	// futurecore/src/main/scala/frontend/ProgramCounter.scala:9:7, :13:26
              `endif // RANDOMIZE_REG_INIT
            end // initial
            `ifdef FIRRTL_AFTER_INITIAL	// futurecore/src/main/scala/frontend/ProgramCounter.scala:9:7
              `FIRRTL_AFTER_INITIAL	// futurecore/src/main/scala/frontend/ProgramCounter.scala:9:7
            `endif // FIRRTL_AFTER_INITIAL
          `endif // ENABLE_INITIAL_REG_
          assign io_instAddr = pc;	// futurecore/src/main/scala/frontend/ProgramCounter.scala:9:7, :13:26
        endmodule
        
        module FutureCore(	// futurecore/src/main/scala/FutureCore.scala:31:7
 000100   input         clock,	// <stdin>:26:11
%000002                 reset,	// <stdin>:27:11
%000000   output [31:0] io_debug_pcInstAddrOutput	// futurecore/src/main/scala/FutureCore.scala:32:14
        );
        
          ProgramCounter pc (	// futurecore/src/main/scala/FutureCore.scala:36:18
            .clock       (clock),
            .reset       (reset),
            .io_instAddr (io_debug_pcInstAddrOutput)
          );
        endmodule

npc/futurecore/sim/logs/vlt_dump.vcd
$version Generated by VerilatedVcd $end
$timescale 1ps $end
 $scope module FutureCore $end
  $var wire 1 # clock $end
  $var wire 1 $ reset $end
  $var wire 32 % io_debug_pcInstAddrOutput [31:0] $end
  $scope module FutureCore $end
   $var wire 1 # clock $end
   $var wire 1 $ reset $end
   $var wire 32 % io_debug_pcInstAddrOutput [31:0] $end
   $scope module pc $end
    $var wire 1 # clock $end
    $var wire 1 $ reset $end
    $var wire 32 % io_instAddr [31:0] $end
    $var wire 32 & pc [31:0] $end
   $upscope $end
  $upscope $end
 $upscope $end
$enddefinitions $end


#1
1#
0$
b00000000000000000000000000000000 %
b00000000000000000000000000000000 &
#2
0#
#3
1#
1$
#4
0#
#5
1#
#6
0#
#7
1#
#8
0#
#9
1#
#10
0#
#11
1#
0$
b00000000000000000000000000000100 %
b00000000000000000000000000000100 &
#12
0#
#13
1#
b00000000000000000000000000001000 %
b00000000000000000000000000001000 &
#14
0#
#15
1#
b00000000000000000000000000001100 %
b00000000000000000000000000001100 &
#16
0#
#17
1#
b00000000000000000000000000010000 %
b00000000000000000000000000010000 &
#18
0#
#19
1#
b00000000000000000000000000010100 %
b00000000000000000000000000010100 &
#20
0#
#21
1#
b00000000000000000000000000011000 %
b00000000000000000000000000011000 &
#22
0#
#23
1#
b00000000000000000000000000011100 %
b00000000000000000000000000011100 &
#24
0#
#25
1#
b00000000000000000000000000100000 %
b00000000000000000000000000100000 &
#26
0#
#27
1#
b00000000000000000000000000100100 %
b00000000000000000000000000100100 &
#28
0#
#29
1#
b00000000000000000000000000101000 %
b00000000000000000000000000101000 &
#30
0#
#31
1#
b00000000000000000000000000101100 %
b00000000000000000000000000101100 &
#32
0#
#33
1#
b00000000000000000000000000110000 %
b00000000000000000000000000110000 &
#34
0#
#35
1#
b00000000000000000000000000110100 %
b00000000000000000000000000110100 &
#36
0#
#37
1#
b00000000000000000000000000111000 %
b00000000000000000000000000111000 &
#38
0#
#39
1#
b00000000000000000000000000111100 %
b00000000000000000000000000111100 &
#40
0#
#41
1#
b00000000000000000000000001000000 %
b00000000000000000000000001000000 &
#42
0#
#43
1#
b00000000000000000000000001000100 %
b00000000000000000000000001000100 &
#44
0#
#45
1#
b00000000000000000000000001001000 %
b00000000000000000000000001001000 &
#46
0#
#47
1#
b00000000000000000000000001001100 %
b00000000000000000000000001001100 &
#48
0#
#49
1#
b00000000000000000000000001010000 %
b00000000000000000000000001010000 &
#50
0#
#51
1#
b00000000000000000000000001010100 %
b00000000000000000000000001010100 &
#52
0#
#53
1#
b00000000000000000000000001011000 %
b00000000000000000000000001011000 &
#54
0#
#55
1#
b00000000000000000000000001011100 %
b00000000000000000000000001011100 &
#56
0#
#57
1#
b00000000000000000000000001100000 %
b00000000000000000000000001100000 &
#58
0#
#59
1#
b00000000000000000000000001100100 %
b00000000000000000000000001100100 &
#60
0#
#61
1#
b00000000000000000000000001101000 %
b00000000000000000000000001101000 &
#62
0#
#63
1#
b00000000000000000000000001101100 %
b00000000000000000000000001101100 &
#64
0#
#65
1#
b00000000000000000000000001110000 %
b00000000000000000000000001110000 &
#66
0#
#67
1#
b00000000000000000000000001110100 %
b00000000000000000000000001110100 &
#68
0#
#69
1#
b00000000000000000000000001111000 %
b00000000000000000000000001111000 &
#70
0#
#71
1#
b00000000000000000000000001111100 %
b00000000000000000000000001111100 &
#72
0#
#73
1#
b00000000000000000000000010000000 %
b00000000000000000000000010000000 &
#74
0#
#75
1#
b00000000000000000000000010000100 %
b00000000000000000000000010000100 &
#76
0#
#77
1#
b00000000000000000000000010001000 %
b00000000000000000000000010001000 &
#78
0#
#79
1#
b00000000000000000000000010001100 %
b00000000000000000000000010001100 &
#80
0#
#81
1#
b00000000000000000000000010010000 %
b00000000000000000000000010010000 &
#82
0#
#83
1#
b00000000000000000000000010010100 %
b00000000000000000000000010010100 &
#84
0#
#85
1#
b00000000000000000000000010011000 %
b00000000000000000000000010011000 &
#86
0#
#87
1#
b00000000000000000000000010011100 %
b00000000000000000000000010011100 &
#88
0#
#89
1#
b00000000000000000000000010100000 %
b00000000000000000000000010100000 &
#90
0#
#91
1#
b00000000000000000000000010100100 %
b00000000000000000000000010100100 &
#92
0#
#93
1#
b00000000000000000000000010101000 %
b00000000000000000000000010101000 &
#94
0#
#95
1#
b00000000000000000000000010101100 %
b00000000000000000000000010101100 &
#96
0#
#97
1#
b00000000000000000000000010110000 %
b00000000000000000000000010110000 &
#98
0#
#99
1#
b00000000000000000000000010110100 %
b00000000000000000000000010110100 &
