npc/make_tracing_c/logs/annotated/sub.v
//      // verilator_coverage annotation
        // DESCRIPTION: Verilator: Verilog Test module
        //
        // This file ONLY is placed under the Creative Commons Public Domain, for
        // any use, without warranty, 2003 by Wilson Snyder.
        // SPDX-License-Identifier: CC0-1.0
        // ======================================================================
        
        module sub
          (
 000016    input clk,
%000003    input reset_l
           );
        
           // Example counter/flop
%000000    reg [31:0] count_c;
%000008    always_ff @ (posedge clk) begin
%000004       if (!reset_l) begin
                 /*AUTORESET*/
                 // Beginning of autoreset for uninitialized flops
%000004          count_c <= 32'h0;
                 // End of automatics
              end
%000004       else begin
%000004          count_c <= count_c + 1;
%000001          if (count_c >= 3) begin
                    // This write is a magic value the Makefile uses to make sure the
                    // test completes successfully.
%000001             $write("*-* All Finished *-*\n");
%000001             $finish;
                 end
              end
           end
        
           // An example assertion
%000008    always_ff @ (posedge clk) begin
%000008       AssertionExample: assert (!reset_l || count_c<100);
           end
        
           // And example coverage analysis
%000001    cover property (@(posedge clk) count_c==3);
        
        endmodule

npc/make_tracing_c/logs/annotated/top.v
//      // verilator_coverage annotation
        // DESCRIPTION: Verilator: Verilog example module
        //
        // This file ONLY is placed under the Creative Commons Public Domain, for
        // any use, without warranty, 2003 by Wilson Snyder.
        // SPDX-License-Identifier: CC0-1.0
        // ======================================================================
        
        // This is intended to be a complex example of several features, please also
        // see the simpler examples/make_hello_c.
        
        module top
          (
           // Declare some signals so we can see how I/O works
 000016    input              clk,
%000003    input              reset_l,
        
%000002    output wire [1:0]  out_small,
%000002    output wire [39:0] out_quad,
%000000    output wire [69:0] out_wide,
%000000    input [1:0]        in_small,
%000001    input [39:0]       in_quad,
%000000    input [69:0]       in_wide
           );
        
           // Connect up the outputs, using some trivial logic
           assign out_small = ~reset_l ? '0 : (in_small + 2'b1);
           assign out_quad  = ~reset_l ? '0 : (in_quad + 40'b1);
           assign out_wide  = ~reset_l ? '0 : (in_wide + 70'b1);
        
           // And an example sub module. The submodule will print stuff.
           sub sub (/*AUTOINST*/
                    // Inputs
                    .clk                        (clk),
                    .reset_l                    (reset_l));
        
           // Print some stuff as an example
%000001    initial begin
%000000       if ($test$plusargs("trace") != 0) begin
%000001          $display("[%0t] Tracing to logs/vlt_dump.vcd...\n", $time);
%000001          $dumpfile("logs/vlt_dump.vcd");
%000001          $dumpvars();
              end
%000001       $display("[%0t] Model running...\n", $time);
           end
        
        endmodule

npc/make_tracing_c/logs/vlt_dump.vcd
$version Generated by VerilatedVcd $end
$timescale 1ps $end
 $scope module TOP $end
  $var wire 1 # clk $end
  $var wire 1 $ reset_l $end
  $var wire 2 % out_small [1:0] $end
  $var wire 40 & out_quad [39:0] $end
  $var wire 70 ( out_wide [69:0] $end
  $var wire 2 + in_small [1:0] $end
  $var wire 40 , in_quad [39:0] $end
  $var wire 70 . in_wide [69:0] $end
  $scope module top $end
   $var wire 1 # clk $end
   $var wire 1 $ reset_l $end
   $var wire 2 % out_small [1:0] $end
   $var wire 40 & out_quad [39:0] $end
   $var wire 70 ( out_wide [69:0] $end
   $var wire 2 + in_small [1:0] $end
   $var wire 40 , in_quad [39:0] $end
   $var wire 70 . in_wide [69:0] $end
   $scope module sub $end
    $var wire 1 # clk $end
    $var wire 1 $ reset_l $end
    $var wire 32 1 count_c [31:0] $end
   $upscope $end
  $upscope $end
 $upscope $end
$enddefinitions $end


#1
1#
1$
b10 %
b0000000000000000000000000001001000110101 &
b0000110010001000100010001000100010001000010001000100010001000100010010 (
b01 +
b0000000000000000000000000001001000110100 ,
b0000110010001000100010001000100010001000010001000100010001000100010001 .
b01011010000110111000010100011110 1
#2
0#
0$
b00 %
b0000000000000000000000000000000000000000 &
b0000000000000000000000000000000000000000000000000000000000000000000000 (
b0000000000000000000000000001001001000110 ,
#3
1#
b00000000000000000000000000000000 1
#4
0#
b0000000000000000000000000001001001011000 ,
#5
1#
#6
0#
b0000000000000000000000000001001001101010 ,
#7
1#
#8
0#
b0000000000000000000000000001001001111100 ,
#9
1#
#10
0#
1$
b10 %
b0000000000000000000000000001001010001111 &
b0000110010001000100010001000100010001000010001000100010001000100010010 (
b0000000000000000000000000001001010001110 ,
#11
1#
b00000000000000000000000000000001 1
#12
0#
b0000000000000000000000000001001010100001 &
b0000000000000000000000000001001010100000 ,
#13
1#
b00000000000000000000000000000010 1
#14
0#
b0000000000000000000000000001001010110011 &
b0000000000000000000000000001001010110010 ,
#15
1#
b00000000000000000000000000000011 1
#16
0#
b0000000000000000000000000001001011000101 &
b0000000000000000000000000001001011000100 ,
#17
1#
b00000000000000000000000000000100 1
